ml4data/__init__.py
ml4data/base.py
ml4data/nlp.py
ml4data/vision.py
ml4data-0.1.2.dist-info/METADATA
ml4data-0.1.2.dist-info/WHEEL
ml4data-0.1.2.dist-info/top_level.txt
ml4data-0.1.2.dist-info/RECORD
