Metadata-Version: 2.1
Name: ml4data
Version: 0.1.2
Summary: A client for ML4Data apis
Home-page: https://ml4data.com/
Author: ML4Data Team
Author-email: ML4Data Team <info@ml4data.com>
Classifier: Programming Language :: Python :: 3
Classifier: License :: OSI Approved :: MIT License
Classifier: Operating System :: OS Independent
Requires-Python: >=3.7
Requires-Dist: requests
Requires-Dist: Pillow
